[
  {
    "FileName": "-1.21.2 Fresh Moves v3.1 (With Animated Eyes).zip",
    "IconUrl": "https://media.forgecdn.net/avatars/thumbnails/985/357/256/256/638494820573552980.png",
    "CurseForgeId": 990406,
    "CurseForgeFileId": 6105672,
    "ModrinthId": null,
    "ModrinthVersionId": null,
    "Author": "Ithan",
    "ProjectName": "Fresh Moves",
    "PreferredReleaseChannel": null,
    "DateAdded": "2026-04-14T06:50:54.165699Z",
    "HasUpdate": false,
    "LatestVersion": null,
    "LatestFileName": null,
    "LatestDownloadUrl": null,
    "LastUpdateCheck": null,
    "DownloadSource": 1,
    "FolderId": null
  },
  {
    "FileName": "FreshCompats_v1.6.zip",
    "IconUrl": "https://media.forgecdn.net/avatars/thumbnails/985/365/256/256/638494825255870634.png",
    "CurseForgeId": 852603,
    "CurseForgeFileId": 5638270,
    "ModrinthId": null,
    "ModrinthVersionId": null,
    "Author": "Ithan",
    "ProjectName": "Fresh Compats (EMF pack)",
    "PreferredReleaseChannel": null,
    "DateAdded": "2026-04-14T06:51:04.0470054Z",
    "HasUpdate": false,
    "LatestVersion": null,
    "LatestFileName": null,
    "LatestDownloadUrl": null,
    "LastUpdateCheck": null,
    "DownloadSource": 1,
    "FolderId": null
  },
  {
    "FileName": "FreshAnimations_v1.10.4.zip",
    "IconUrl": "https://cdn.modrinth.com/data/50dA9Sha/3132c10e9e3c73fde9799720fd3da5561071708c_96.webp",
    "CurseForgeId": 453763,
    "CurseForgeFileId": 7670377,
    "ModrinthId": "50dA9Sha",
    "ModrinthVersionId": "xN57JJts",
    "Author": "FreshLX",
    "ProjectName": "Fresh Animations",
    "PreferredReleaseChannel": null,
    "DateAdded": "2026-04-14T06:52:10.4333712Z",
    "HasUpdate": false,
    "LatestVersion": null,
    "LatestFileName": null,
    "LatestDownloadUrl": null,
    "LastUpdateCheck": null,
    "DownloadSource": 2,
    "FolderId": null
  },
  {
    "FileName": "FA\u002BAll_Extensions-v1.8.zip",
    "IconUrl": "https://cdn.modrinth.com/data/YAVTU8mK/2e83da75469cdec6d4558023cba611443b105c9e_96.webp",
    "CurseForgeId": 813608,
    "CurseForgeFileId": 7674538,
    "ModrinthId": "YAVTU8mK",
    "ModrinthVersionId": "9rbQZuzp",
    "Author": "FreshLX",
    "ProjectName": "Fresh Animations: Extensions",
    "PreferredReleaseChannel": null,
    "DateAdded": "2026-04-14T06:58:41.7745127Z",
    "HasUpdate": false,
    "LatestVersion": null,
    "LatestFileName": null,
    "LatestDownloadUrl": null,
    "LastUpdateCheck": null,
    "DownloadSource": 2,
    "FolderId": null
  },
  {
    "FileName": "FA\u002BPlayer-v1.0.zip",
    "IconUrl": "https://media.forgecdn.net/avatars/thumbnails/1583/647/256/256/639025156581167648.png",
    "CurseForgeId": 1281029,
    "CurseForgeFileId": 7420591,
    "ModrinthId": null,
    "ModrinthVersionId": null,
    "Author": "FreshLX",
    "ProjectName": "Fresh Animations: Player Extension",
    "PreferredReleaseChannel": null,
    "DateAdded": "2026-04-15T02:55:06.6001745Z",
    "HasUpdate": false,
    "LatestVersion": null,
    "LatestFileName": null,
    "LatestDownloadUrl": null,
    "LastUpdateCheck": null,
    "DownloadSource": 1,
    "FolderId": null
  },
  {
    "FileName": "FA\u002BEmissive-v1.5.zip",
    "IconUrl": "https://media.forgecdn.net/avatars/thumbnails/1443/771/256/256/638936240323663025.png",
    "CurseForgeId": 1346083,
    "CurseForgeFileId": 7674560,
    "ModrinthId": null,
    "ModrinthVersionId": null,
    "Author": "FreshLX",
    "ProjectName": "Fresh Animations: Emissive",
    "PreferredReleaseChannel": null,
    "DateAdded": "2026-04-15T02:56:07.3022585Z",
    "HasUpdate": false,
    "LatestVersion": null,
    "LatestFileName": null,
    "LatestDownloadUrl": null,
    "LastUpdateCheck": null,
    "DownloadSource": 1,
    "FolderId": null
  },
  {
    "FileName": "FA\u002BDetails-v2.2.zip",
    "IconUrl": "https://media.forgecdn.net/avatars/thumbnails/1443/739/256/256/638936221969112442.png",
    "CurseForgeId": 1346132,
    "CurseForgeFileId": 7674533,
    "ModrinthId": null,
    "ModrinthVersionId": null,
    "Author": "FreshLX",
    "ProjectName": "Fresh Animations: Details",
    "PreferredReleaseChannel": null,
    "DateAdded": "2026-04-15T02:56:31.8184772Z",
    "HasUpdate": false,
    "LatestVersion": null,
    "LatestFileName": null,
    "LatestDownloadUrl": null,
    "LastUpdateCheck": null,
    "DownloadSource": 1,
    "FolderId": null
  }
]